dedlin/__about__.py
dedlin/__init__.py
dedlin/__main__.py
dedlin/ai_interface.py
dedlin/basic_types.py
dedlin/command_sources.py
dedlin/document.py
dedlin/document_sources.py
dedlin/file_converters.py
dedlin/file_system.py
dedlin/flash.py
dedlin/history_feature.py
dedlin/logging_utils.py
dedlin/main.py
dedlin/outputters/__init__.py
dedlin/outputters/plain.py
dedlin/outputters/rich_output.py
dedlin/outputters/talking_outputter.py
dedlin/parsers.md
dedlin/parsers.py
dedlin/py.typed
dedlin/pygments_code.py
dedlin/string_comands.py
dedlin/text/__init__.py
dedlin/text/help_text.py
dedlin/tools/__init__.py
dedlin/tools/export.py
dedlin/tools/info_bar.py
dedlin/tools/lorem_data.py
dedlin/tools/spelling_overlay.py
dedlin/tools/web.py
dedlin/ui_exit.py
dedlin/utils/__init__.py
dedlin/utils/exceptions.py
dedlin/utils/file_utils.py
dedlin-1.19.4.dist-info/LICENSE
dedlin-1.19.4.dist-info/METADATA
dedlin-1.19.4.dist-info/WHEEL
dedlin-1.19.4.dist-info/entry_points.txt
dedlin-1.19.4.dist-info/RECORD
