Metadata-Version: 2.1
Name: dedlin
Version: 1.19.4
Summary: Line editor, edlin clone with many improvements
Home-page: https://github.com/matthewdeanmartin/dedlin
License: MIT
Keywords: editor,edlin,line editor
Author: Matthew Martin
Author-email: matthewdeanmartin@gmail.com
Requires-Python: >=3.11,<4.0.0
Classifier: Development Status :: 5 - Production/Stable
Classifier: Intended Audience :: Developers
Classifier: License :: OSI Approved :: MIT License
Classifier: Operating System :: OS Independent
Classifier: Programming Language :: Python
Classifier: Programming Language :: Python :: 3
Classifier: Programming Language :: Python :: 3.11
Classifier: Programming Language :: Python :: 3.12
Classifier: Programming Language :: Python :: 3.13
Provides-Extra: speaking
Requires-Dist: art (>=6.1,<7)
Requires-Dist: docopt-ng (>=0.9.0)
Requires-Dist: html2text (>=2020.1.16)
Requires-Dist: icontract (>=2.6.4,<3)
Requires-Dist: markdown-it-py (>=3.0.0,<4)
Requires-Dist: mistune (<3.0.0)
Requires-Dist: openai (>=1.3.8)
Requires-Dist: pydantic (>2.0.0,<3)
Requires-Dist: pygments (>=2.16.1,<3)
Requires-Dist: pyspellchecker (>=0.7.2)
Requires-Dist: python-dotenv (>=1.0.0)
Requires-Dist: pywin32 (>=228) ; sys_platform == "win32"
Requires-Dist: questionary (>=2.0.1,<3)
Requires-Dist: requests (>=2.31.0)
Requires-Dist: rich (>=13.7.0,<14)
Requires-Dist: setuptools
Requires-Dist: textstat (>=0.7.3)
Project-URL: Bug Tracker, https://github.com/matthewdeanmartin/dedlin/issues
Project-URL: Change Log, https://github.com/matthewdeanmartin/dedlin/blob/main/CHANGES.md
Project-URL: Documentation, https://github.com/matthewdeanmartin/dedlin
Project-URL: Repository, https://github.com/matthewdeanmartin/dedlin
